{
  "$schema": "https://json-schema.org/draft/2020-12/schema",
  "$id": "http://smart.who.int/immunizations/ValueSet-IMMZ.D2.DT.Meningococcal.MenC.schema.json",
  "title": "IMMZ.D2.DT.Meningococcal.MenC ValueSet for Decision Table Schema",
  "description": "JSON Schema for IMMZ.D2.DT.Meningococcal.MenC ValueSet for Decision Table ValueSet codes. Generated from FHIR expansions.",
  "type": "string",
  "enum": [
    "nmpsdwa-53.130",
    "ompsdwa-54.130",
    "tmpsdwa-56.130",
    "csailt2m-34.43",
    "csaimtoet2m-46.43",
    "csawltoet1mwtpsws-84.118",
    "tlmdwalt2ma-69.112",
    "tlmdwamt2ma-69.112",
    "csawmt1mwtpsws-72.118",
    "tlmdwalt1ya-67.117",
    "nmbdwa-46.128",
    "tlmdwamt1ya-67.117",
    "mbdwa-43.128",
    "cindfmv-47.52",
    "cidfmv-43.48",
    "misic-47.53",
    "tpsiccidfmbd-76.48"
  ],
  "narrative": "This schema validates codes for the IMMZ.D2.DT.Meningococcal.MenC ValueSet for Decision Table ValueSet. Display values are available at ValueSet-IMMZ.D2.DT.Meningococcal.MenC.displays.json. System URI mappings are available at ValueSet-IMMZ.D2.DT.Meningococcal.MenC.system.json.",
  "fhir:displays": "ValueSet-IMMZ.D2.DT.Meningococcal.MenC.displays.json",
  "fhir:system": "ValueSet-IMMZ.D2.DT.Meningococcal.MenC.system.json",
  "fhir:valueSet": "http://smart.who.int/immunizations/ValueSet/IMMZ.D2.DT.Meningococcal.MenC",
  "fhir:version": "0.2.0",
  "fhir:expansionTimestamp": "2025-06-25T16:39:07.092Z"
}