<?xml version="1.0" encoding="UTF-8"?>

<ValueSet xmlns="http://hl7.org/fhir">
  <id value="IMMZD2DTMumpsVS"/>
  <text>
    <status value="generated"/><div xmlns="http://www.w3.org/1999/xhtml"><p class="res-header-id"><b>Generated Narrative: ValueSet IMMZD2DTMumpsVS</b></p><a name="IMMZD2DTMumpsVS"> </a><a name="hcIMMZD2DTMumpsVS"> </a><p>This value set expansion contains 12 concepts.</p><table class="codes"><tr><td><b>System</b></td><td style="white-space:nowrap"><b>Code</b></td><td><b>Display</b></td></tr><tr><td><a name="IMMZD2DTMumpsVS-http://smart.who.int/immunizations/CodeSystem/IMMZDAK-Client's|20age|20is|20less|20than|2012|20months-42"> </a><code>http://smart.who.int/immunizations/CodeSystem/IMMZDAK</code></td><td style="white-space:nowrap">  <a href="CodeSystem-IMMZDAK.html#IMMZDAK-Client.39sageislessthan12months-42">Client's age is less than 12 months-42</a></td><td>Client's age is less than 12 months</td></tr><tr><td><a name="IMMZD2DTMumpsVS-http://smart.who.int/immunizations/CodeSystem/IMMZDAK-Client|20is|20not|20due|20for|20mumps|20vaccination-48"> </a><code>http://smart.who.int/immunizations/CodeSystem/IMMZDAK</code></td><td style="white-space:nowrap">  <a href="CodeSystem-IMMZDAK.html#IMMZDAK-Clientisnotdueformumpsvaccination-48">Client is not due for mumps vaccination-48</a></td><td>Client is not due for mumps vaccination</td></tr><tr><td><a name="IMMZD2DTMumpsVS-http://smart.who.int/immunizations/CodeSystem/IMMZDAK-No|20mumps|20primary|20series|20doses|20were|20administered-125"> </a><code>http://smart.who.int/immunizations/CodeSystem/IMMZDAK</code></td><td style="white-space:nowrap">  <a href="CodeSystem-IMMZDAK.html#IMMZDAK-Nomumpsprimaryseriesdoseswereadministered-125">No mumps primary series doses were administered-125</a></td><td>No mumps primary series doses were administered</td></tr><tr><td><a name="IMMZD2DTMumpsVS-http://smart.who.int/immunizations/CodeSystem/IMMZDAK-Client's|20age|20is|20more|20than|20or|20equal|20to|2012|20months-42"> </a><code>http://smart.who.int/immunizations/CodeSystem/IMMZDAK</code></td><td style="white-space:nowrap">  <a href="CodeSystem-IMMZDAK.html#IMMZDAK-Client.39sageismorethanorequalto12months-42">Client's age is more than or equal to 12 months-42</a></td><td>Client's age is more than or equal to 12 months</td></tr><tr><td><a name="IMMZD2DTMumpsVS-http://smart.who.int/immunizations/CodeSystem/IMMZDAK-Live|20vaccine|20was|20administered|20in|20the|20past|204|20weeks-92"> </a><code>http://smart.who.int/immunizations/CodeSystem/IMMZDAK</code></td><td style="white-space:nowrap">  <a href="CodeSystem-IMMZDAK.html#IMMZDAK-Livevaccinewasadministeredinthepast4weeks-92">Live vaccine was administered in the past 4 weeks-92</a></td><td>Live vaccine was administered in the past 4 weeks</td></tr><tr><td><a name="IMMZD2DTMumpsVS-http://smart.who.int/immunizations/CodeSystem/IMMZDAK-No|20live|20vaccine|20was|20administered|20in|20the|20past|204|20weeks-92"> </a><code>http://smart.who.int/immunizations/CodeSystem/IMMZDAK</code></td><td style="white-space:nowrap">  <a href="CodeSystem-IMMZDAK.html#IMMZDAK-Nolivevaccinewasadministeredinthepast4weeks-92">No live vaccine was administered in the past 4 weeks-92</a></td><td>No live vaccine was administered in the past 4 weeks</td></tr><tr><td><a name="IMMZD2DTMumpsVS-http://smart.who.int/immunizations/CodeSystem/IMMZDAK-Client|20is|20due|20for|20mumps|20vaccination-44"> </a><code>http://smart.who.int/immunizations/CodeSystem/IMMZDAK</code></td><td style="white-space:nowrap">  <a href="CodeSystem-IMMZDAK.html#IMMZDAK-Clientisdueformumpsvaccination-44">Client is due for mumps vaccination-44</a></td><td>Client is due for mumps vaccination</td></tr><tr><td><a name="IMMZD2DTMumpsVS-http://smart.who.int/immunizations/CodeSystem/IMMZDAK-One|20mumps|20primary|20series|20dose|20was|20administered-125"> </a><code>http://smart.who.int/immunizations/CodeSystem/IMMZDAK</code></td><td style="white-space:nowrap">  <a href="CodeSystem-IMMZDAK.html#IMMZDAK-Onemumpsprimaryseriesdosewasadministered-125">One mumps primary series dose was administered-125</a></td><td>One mumps primary series dose was administered</td></tr><tr><td><a name="IMMZD2DTMumpsVS-http://smart.who.int/immunizations/CodeSystem/IMMZDAK-The|20latest|20mumps|20dose|20was|20administered|20less|20than|204|20weeks|20ago-108"> </a><code>http://smart.who.int/immunizations/CodeSystem/IMMZDAK</code></td><td style="white-space:nowrap">  <a href="CodeSystem-IMMZDAK.html#IMMZDAK-Thelatestmumpsdosewasadministeredlessthan4weeksago-108">The latest mumps dose was administered less than 4 weeks ago-108</a></td><td>The latest mumps dose was administered less than 4 weeks ago</td></tr><tr><td><a name="IMMZD2DTMumpsVS-http://smart.who.int/immunizations/CodeSystem/IMMZDAK-The|20latest|20mumps|20dose|20was|20administered|20more|20than|204|20weeks|20ago-108"> </a><code>http://smart.who.int/immunizations/CodeSystem/IMMZDAK</code></td><td style="white-space:nowrap">  <a href="CodeSystem-IMMZDAK.html#IMMZDAK-Thelatestmumpsdosewasadministeredmorethan4weeksago-108">The latest mumps dose was administered more than 4 weeks ago-108</a></td><td>The latest mumps dose was administered more than 4 weeks ago</td></tr><tr><td><a name="IMMZD2DTMumpsVS-http://smart.who.int/immunizations/CodeSystem/IMMZDAK-Two|20mumps|20primary|20series|20doses|20were|20administered-125"> </a><code>http://smart.who.int/immunizations/CodeSystem/IMMZDAK</code></td><td style="white-space:nowrap">  <a href="CodeSystem-IMMZDAK.html#IMMZDAK-Twomumpsprimaryseriesdoseswereadministered-125">Two mumps primary series doses were administered-125</a></td><td>Two mumps primary series doses were administered</td></tr><tr><td><a name="IMMZD2DTMumpsVS-http://smart.who.int/immunizations/CodeSystem/IMMZDAK-Mumps|20immunization|20schedule|20is|20complete-153"> </a><code>http://smart.who.int/immunizations/CodeSystem/IMMZDAK</code></td><td style="white-space:nowrap">  <a href="CodeSystem-IMMZDAK.html#IMMZDAK-Mumpsimmunizationscheduleiscomplete-153">Mumps immunization schedule is complete-153</a></td><td>Mumps immunization schedule is complete</td></tr></table></div>
  </text>
  <url value="http://smart.who.int/immunizations/ValueSet/IMMZD2DTMumpsVS"/>
  <version value="0.2.0"/>
  <name value="IMMZD2DTMumpsVS"/>
  <title value="IMMZD2DTMumps ValueSet for Decision Table"/>
  <status value="active"/>
  <date value="2025-11-25T19:41:02+00:00"/>
  <publisher value="WHO"/>
  <contact>
    <name value="WHO"/>
    <telecom>
      <system value="url"/>
      <value value="http://who.int"/>
    </telecom>
  </contact>
  <description value="ValueSet IMMZD2DTMumps for IMMZ.D2.DT.Mumps.&#xA;Business rule: Determine if the client is due for a mumps vaccination according to the national immunization schedule&#xA;Trigger: IMMZ.D2 Determine required vaccination(s) if any&#xA;Table: 2-dose schedule (countries with mumps in schedule and low transmission of measles)"/>
  <compose>
    <include>
      <system value="http://smart.who.int/immunizations/CodeSystem/IMMZDAK"/>
      <concept>
        <code value="Client's age is less than 12 months-42"/>
        <display value="Client's age is less than 12 months"/>
      </concept>
      <concept>
        <code value="Client is not due for mumps vaccination-48"/>
        <display value="Client is not due for mumps vaccination"/>
      </concept>
      <concept>
        <code value="No mumps primary series doses were administered-125"/>
        <display value="No mumps primary series doses were administered"/>
      </concept>
      <concept>
        <code value="Client's age is more than or equal to 12 months-42"/>
        <display value="Client's age is more than or equal to 12 months"/>
      </concept>
      <concept>
        <code value="Live vaccine was administered in the past 4 weeks-92"/>
        <display value="Live vaccine was administered in the past 4 weeks"/>
      </concept>
      <concept>
        <code value="No live vaccine was administered in the past 4 weeks-92"/>
        <display value="No live vaccine was administered in the past 4 weeks"/>
      </concept>
      <concept>
        <code value="Client is due for mumps vaccination-44"/>
        <display value="Client is due for mumps vaccination"/>
      </concept>
      <concept>
        <code value="One mumps primary series dose was administered-125"/>
        <display value="One mumps primary series dose was administered"/>
      </concept>
      <concept>
        <code value="The latest mumps dose was administered less than 4 weeks ago-108"/>
        <display value="The latest mumps dose was administered less than 4 weeks ago"/>
      </concept>
      <concept>
        <code value="The latest mumps dose was administered more than 4 weeks ago-108"/>
        <display value="The latest mumps dose was administered more than 4 weeks ago"/>
      </concept>
      <concept>
        <code value="Two mumps primary series doses were administered-125"/>
        <display value="Two mumps primary series doses were administered"/>
      </concept>
      <concept>
        <code value="Mumps immunization schedule is complete-153"/>
        <display value="Mumps immunization schedule is complete"/>
      </concept>
    </include>
  </compose>
  <expansion>
    <timestamp value="2025-09-29T20:59:26.458Z"/>
    <contains>
      <system value="http://smart.who.int/immunizations/CodeSystem/IMMZDAK"/>
      <code value="Client's age is less than 12 months-42"/>
      <display value="Client's age is less than 12 months"/>
    </contains>
    <contains>
      <system value="http://smart.who.int/immunizations/CodeSystem/IMMZDAK"/>
      <code value="Client is not due for mumps vaccination-48"/>
      <display value="Client is not due for mumps vaccination"/>
    </contains>
    <contains>
      <system value="http://smart.who.int/immunizations/CodeSystem/IMMZDAK"/>
      <code value="No mumps primary series doses were administered-125"/>
      <display value="No mumps primary series doses were administered"/>
    </contains>
    <contains>
      <system value="http://smart.who.int/immunizations/CodeSystem/IMMZDAK"/>
      <code value="Client's age is more than or equal to 12 months-42"/>
      <display value="Client's age is more than or equal to 12 months"/>
    </contains>
    <contains>
      <system value="http://smart.who.int/immunizations/CodeSystem/IMMZDAK"/>
      <code value="Live vaccine was administered in the past 4 weeks-92"/>
      <display value="Live vaccine was administered in the past 4 weeks"/>
    </contains>
    <contains>
      <system value="http://smart.who.int/immunizations/CodeSystem/IMMZDAK"/>
      <code value="No live vaccine was administered in the past 4 weeks-92"/>
      <display value="No live vaccine was administered in the past 4 weeks"/>
    </contains>
    <contains>
      <system value="http://smart.who.int/immunizations/CodeSystem/IMMZDAK"/>
      <code value="Client is due for mumps vaccination-44"/>
      <display value="Client is due for mumps vaccination"/>
    </contains>
    <contains>
      <system value="http://smart.who.int/immunizations/CodeSystem/IMMZDAK"/>
      <code value="One mumps primary series dose was administered-125"/>
      <display value="One mumps primary series dose was administered"/>
    </contains>
    <contains>
      <system value="http://smart.who.int/immunizations/CodeSystem/IMMZDAK"/>
      <code value="The latest mumps dose was administered less than 4 weeks ago-108"/>
      <display value="The latest mumps dose was administered less than 4 weeks ago"/>
    </contains>
    <contains>
      <system value="http://smart.who.int/immunizations/CodeSystem/IMMZDAK"/>
      <code value="The latest mumps dose was administered more than 4 weeks ago-108"/>
      <display value="The latest mumps dose was administered more than 4 weeks ago"/>
    </contains>
    <contains>
      <system value="http://smart.who.int/immunizations/CodeSystem/IMMZDAK"/>
      <code value="Two mumps primary series doses were administered-125"/>
      <display value="Two mumps primary series doses were administered"/>
    </contains>
    <contains>
      <system value="http://smart.who.int/immunizations/CodeSystem/IMMZDAK"/>
      <code value="Mumps immunization schedule is complete-153"/>
      <display value="Mumps immunization schedule is complete"/>
    </contains>
  </expansion>
</ValueSet>