{
  "resourceType": "Library",
  "id": "IMMZD5DTRabiesEncounterElements",
  "meta": {
    "profile": [
      "http://hl7.org/fhir/uv/crmi/StructureDefinition/crmi-shareablelibrary",
      "http://hl7.org/fhir/uv/crmi/StructureDefinition/crmi-publishablelibrary",
      "http://hl7.org/fhir/uv/cql/StructureDefinition/cql-library",
      "http://hl7.org/fhir/uv/cql/StructureDefinition/cql-module"
    ]
  },
  "text": {
    "status": "extensions",
    "div": "<div xmlns=\"http://www.w3.org/1999/xhtml\">\n<div>\n    <table class=\"grid dict\">\n        \n        \n        <tr>\n            <th scope=\"row\"><b>Title: </b></th>\n            <td style=\"padding-left: 4px;\">IMMZD5DTRabiesEncounterElements</td>\n        </tr>\n        \n\n        \n        \n        <tr>\n            <th scope=\"row\"><b>Id: </b></th>\n            <td style=\"padding-left: 4px;\">IMMZD5DTRabiesEncounterElements</td>\n        </tr>\n        \n\n        \n        \n        <tr>\n            <th scope=\"row\"><b>Version: </b></th>\n            <td style=\"padding-left: 4px;\">0.2.0</td>\n        </tr>\n        \n\n        \n        <tr>\n            <th scope=\"row\"><b>Url: </b></th>\n            <td style=\"padding-left: 4px;\"><a href=\"Library-IMMZD5DTRabiesEncounterElements.html\">IMMZD5DTRabiesEncounterElements</a></td>\n        </tr>\n        \n\n        \n\n        \n\n        \n        <tr>\n            <th scope=\"row\"><b>Status: </b></th>\n            <td style=\"padding-left: 4px;\">draft</td>\n        </tr>\n        \n\n        \n\n        \n        <tr>\n            <th scope=\"row\"><b>Type: </b></th>\n            <td style=\"padding-left: 4px;\">\n                \n                    \n                        \n                        <p style=\"margin-bottom: 5px;\">\n                            <b>system: </b> <span><a href=\"http://terminology.hl7.org/7.1.0/CodeSystem-library-type.html\">http://terminology.hl7.org/CodeSystem/library-type</a></span>\n                        </p>\n                        \n                        \n                        <p style=\"margin-bottom: 5px;\">\n                            <b>code: </b> <span>logic-library</span>\n                        </p>\n                        \n                        \n                    \n                \n                \n            </td>\n        </tr>\n        \n\n        \n\n        \n        <tr>\n            <th scope=\"row\"><b>Date: </b></th>\n            <td style=\"padding-left: 4px;\">2026-04-03 22:35:55+0000</td>\n        </tr>\n        \n\n        \n        <tr>\n            <th scope=\"row\"><b>Publisher: </b></th>\n            <td style=\"padding-left: 4px;\">WHO</td>\n        </tr>\n        \n\n        \n        <tr>\n            <th scope=\"row\"><b>Description: </b></th>\n            <td style=\"padding-left: 4px;\"><div><p>This library defines encounter-based elements for Rabies used throughout the Immunization CPG</p>\n</div></td>\n        </tr>\n        \n\n        \n\n        \n\n        \n\n        \n\n        \n\n        \n\n        \n\n        \n\n        \n\n        \n\n        \n        <tr>\n            <th scope=\"row\"><b>Related Artifacts: </b></th>\n            <td style=\"padding-left: 4px;\">\n                \n                \n                \n                <p><b>Dependencies</b></p>\n                <ul>\n                  \n                    <li><a href=\"Library-WHOConcepts.html\">WHOConcepts</a></li>\n                  \n                    <li><a href=\"Library-WHOCommon.html\">WHOCommon</a></li>\n                  \n                    <li><a href=\"Library-WHOElements.html\">WHOElements</a></li>\n                  \n                    <li><a href=\"Library-IMMZCommon.html\">IMMZCommon</a></li>\n                  \n                    <li><a href=\"Library-IMMZConcepts.html\">IMMZConcepts</a></li>\n                  \n                    <li><a href=\"Library-IMMZEncounterElements.html\">IMMZEncounterElements</a></li>\n                  \n                    <li><a href=\"Library-IMMZD5DTRabiesElements.html\">IMMZD5DTRabiesElements</a></li>\n                  \n                </ul>\n                \n                \n                \n                \n                \n            </td>\n        </tr>\n        \n\n        \n        <tr>\n          <th scope=\"row\"><b>Parameters: </b></th>\n          <td style=\"padding-left: 4px;\">\n            <table class=\"grid-dict\">\n              <tr><th><b>Name</b></th><th><b>Type</b></th><th><b>Min</b></th><th><b>Max</b></th><th><b>In/Out</b></th></tr>\n              \n                <tr><th>Today</th><th>date</th><th>0</th><th>1</th><th>In</th></tr>\n              \n                <tr><th>EncounterId</th><th>string</th><th>0</th><th>1</th><th>In</th></tr>\n              \n                <tr><th>Patient</th><th>Patient</th><th>0</th><th>1</th><th>Out</th></tr>\n              \n                <tr><th>Draft Medication Request for Rabies dose</th><th>MedicationRequest</th><th>0</th><th>*</th><th>Out</th></tr>\n              \n                <tr><th>The client has history of severe allergic reactions</th><th>boolean</th><th>0</th><th>1</th><th>Out</th></tr>\n              \n            </table>\n          </td>\n        </tr>\n        \n\n        \n\n        \n        \n        <tr>\n          <td colspan=\"2\">\n            <table>\n              <tr><th><a id=\"cql-content\"><b>Content: </b></a> text/cql</th></tr>\n              <tr><td><pre><code class=\"language-cql\">\n/*\n  * Library: IMMZD5DTRabiesEncounterElements\n  */\nlibrary IMMZD5DTRabiesEncounterElements\n\nusing FHIR version '4.0.1'\ninclude FHIRHelpers version '4.0.1'\n\ninclude WHOConcepts\ninclude WHOCommon called WC\ninclude WHOElements called WE\n\ninclude IMMZCommon called Common\ninclude IMMZConcepts called Concepts\ninclude IMMZEncounterElements called Encounter\n\ninclude IMMZD5DTRabiesElements called RabiesElements\n\nparameter Today Date default Today()\nparameter EncounterId String\n\ncontext Patient\n\n/*\n@internal: Draft Medication Request for Rabies dose\n*/\ndefine &quot;Draft Medication Request for Rabies dose&quot;:\n  Encounter.&quot;Draft Medication Request for Patient&quot; MR\n    where MR.medication in Concepts.&quot;Rabies vaccines&quot;\n\n/*\n@input: The client has history of severe allergic reactions\n@pseudocode: &quot;Potential contraindications&quot; = &quot;Severe allergic reactions&quot;\n@code: The client has history of severe allergic reactions-59\n@decision: IMMZ.D5.DT.Rabies contraindications\n*/\ndefine &quot;The client has history of severe allergic reactions&quot;:\n  Encounter.&quot;The client has history of severe allergic reactions&quot;\n</code></pre></td></tr>\n            </table>\n          </td>\n        </tr>\n        \n        \n        \n        \n        \n        <tr>\n          <td colspan=\"2\">\n            <table>\n              <tr><th><b>Content: </b> application/elm+xml</th></tr>\n              <tr><td><pre><code>Encoded data (15148 characters)</code></pre></td></tr>\n            </table>\n          </td>\n        </tr>\n        \n        \n    </table>\n</div>\n</div>"
  },
  "extension": [
    {
      "url": "http://hl7.org/fhir/StructureDefinition/cqf-knowledgeCapability",
      "valueCode": "computable"
    }
  ],
  "url": "http://smart.who.int/immunizations/Library/IMMZD5DTRabiesEncounterElements",
  "version": "0.2.0",
  "name": "IMMZD5DTRabiesEncounterElements",
  "title": "IMMZD5DTRabiesEncounterElements",
  "status": "draft",
  "experimental": false,
  "type": {
    "coding": [
      {
        "system": "http://terminology.hl7.org/CodeSystem/library-type",
        "code": "logic-library"
      }
    ]
  },
  "date": "2026-04-03T22:35:55+00:00",
  "publisher": "WHO",
  "contact": [
    {
      "name": "WHO",
      "telecom": [
        {
          "system": "url",
          "value": "http://who.int"
        }
      ]
    }
  ],
  "description": "This library defines encounter-based elements for Rabies used throughout the Immunization CPG",
  "relatedArtifact": [
    {
      "type": "depends-on",
      "display": "Library WHOConcepts",
      "resource": "http://smart.who.int/immunizations/Library/WHOConcepts"
    },
    {
      "type": "depends-on",
      "display": "Library WC",
      "resource": "http://smart.who.int/immunizations/Library/WHOCommon"
    },
    {
      "type": "depends-on",
      "display": "Library WE",
      "resource": "http://smart.who.int/immunizations/Library/WHOElements"
    },
    {
      "type": "depends-on",
      "display": "Library Common",
      "resource": "http://smart.who.int/immunizations/Library/IMMZCommon"
    },
    {
      "type": "depends-on",
      "display": "Library Concepts",
      "resource": "http://smart.who.int/immunizations/Library/IMMZConcepts"
    },
    {
      "type": "depends-on",
      "display": "Library Encounter",
      "resource": "http://smart.who.int/immunizations/Library/IMMZEncounterElements"
    },
    {
      "type": "depends-on",
      "display": "Library RabiesElements",
      "resource": "http://smart.who.int/immunizations/Library/IMMZD5DTRabiesElements"
    }
  ],
  "parameter": [
    {
      "name": "Today",
      "use": "in",
      "min": 0,
      "max": "1",
      "type": "date"
    },
    {
      "name": "EncounterId",
      "use": "in",
      "min": 0,
      "max": "1",
      "type": "string"
    },
    {
      "name": "Patient",
      "use": "out",
      "min": 0,
      "max": "1",
      "type": "Patient"
    },
    {
      "name": "Draft Medication Request for Rabies dose",
      "use": "out",
      "min": 0,
      "max": "*",
      "type": "MedicationRequest"
    },
    {
      "name": "The client has history of severe allergic reactions",
      "use": "out",
      "min": 0,
      "max": "1",
      "type": "boolean"
    }
  ],
  "content": [
    {
      "contentType": "text/cql",
      "url": "Library-IMMZD5DTRabiesEncounterElements.cql"
    },
    {
      "contentType": "application/elm+xml",
      "url": "Library-IMMZD5DTRabiesEncounterElements.elm.xml"
    }
  ]
}
